{
  "id": "MAP_BLACK_KNIGHTS_FORTRESS_4",
  "name": "Black_Knights_Fortress_4",
  "layout": "LAYOUT_BLACK_KNIGHTS_FORTRESS_4",
  "music": "MUS_PS_KOUREND_CATACOMBS",
  "region_map_section": "MAPSEC_ICE_MOUNTAIN",
  "requires_flash": false,
  "weather": "WEATHER_NONE",
  "map_type": "MAP_TYPE_INDOOR",
  "allow_cycling": false,
  "allow_escaping": false,
  "allow_running": true,
  "show_map_name": false,
  "battle_scene": "MAP_BATTLE_SCENE_NORMAL",
  "connections": 0,
  "object_events": [
    {
      "graphics_id": "OBJ_EVENT_GFX_KNIGHT_BLACK_DAQUARIUS",
      "x": 18,
      "y": 2,
      "elevation": 0,
      "movement_type": "MOVEMENT_TYPE_NONE",
      "movement_range_x": 0,
      "movement_range_y": 0,
      "trainer_type": "TRAINER_TYPE_NONE",
      "trainer_sight_or_berry_tree_id": "0",
      "script": "NULL",
      "flag": "0"
    },
    {
      "graphics_id": "OBJ_EVENT_GFX_HAM_SIGMUND_1",
      "x": 18,
      "y": 5,
      "elevation": 0,
      "movement_type": "MOVEMENT_TYPE_FACE_UP",
      "movement_range_x": 0,
      "movement_range_y": 0,
      "trainer_type": "TRAINER_TYPE_NONE",
      "trainer_sight_or_berry_tree_id": "0",
      "script": "NULL",
      "flag": "0"
    },
    {
      "graphics_id": "OBJ_EVENT_GFX_ELITE_BLACK_KNIGHT",
      "x": 16,
      "y": 2,
      "elevation": 0,
      "movement_type": "MOVEMENT_TYPE_NONE",
      "movement_range_x": 0,
      "movement_range_y": 0,
      "trainer_type": "TRAINER_TYPE_NONE",
      "trainer_sight_or_berry_tree_id": "0",
      "script": "BKFORT_4F_NPC_8",
      "flag": "0"
    },
    {
      "graphics_id": "OBJ_EVENT_GFX_ELITE_BLACK_KNIGHT",
      "x": 20,
      "y": 2,
      "elevation": 0,
      "movement_type": "MOVEMENT_TYPE_NONE",
      "movement_range_x": 0,
      "movement_range_y": 0,
      "trainer_type": "TRAINER_TYPE_NONE",
      "trainer_sight_or_berry_tree_id": "0",
      "script": "BKFORT_4F_NPC_9",
      "flag": "0"
    },
    {
      "graphics_id": "OBJ_EVENT_GFX_KNIGHT_BLACK_F",
      "x": 1,
      "y": 12,
      "elevation": 0,
      "movement_type": "MOVEMENT_TYPE_FACE_RIGHT",
      "movement_range_x": 0,
      "movement_range_y": 0,
      "trainer_type": "TRAINER_TYPE_NONE",
      "trainer_sight_or_berry_tree_id": "0",
      "script": "BKFORT_4F_NPC_5",
      "flag": "0"
    },
    {
      "graphics_id": "OBJ_EVENT_GFX_KNIGHT_BLACK_M",
      "x": 3,
      "y": 12,
      "elevation": 0,
      "movement_type": "MOVEMENT_TYPE_FACE_LEFT",
      "movement_range_x": 0,
      "movement_range_y": 0,
      "trainer_type": "TRAINER_TYPE_NONE",
      "trainer_sight_or_berry_tree_id": "0",
      "script": "BKFORT_4F_NPC_6",
      "flag": "0"
    },
    {
      "graphics_id": "OBJ_EVENT_GFX_KNIGHT_BLACK_F",
      "x": 18,
      "y": 21,
      "elevation": 0,
      "movement_type": "MOVEMENT_TYPE_FACE_LEFT",
      "movement_range_x": 0,
      "movement_range_y": 0,
      "trainer_type": "TRAINER_TYPE_NONE",
      "trainer_sight_or_berry_tree_id": "0",
      "script": "BKFORT_4F_NPC_4",
      "flag": "0"
    },
    {
      "graphics_id": "OBJ_EVENT_GFX_KNIGHT_BLACK_M",
      "x": 14,
      "y": 21,
      "elevation": 0,
      "movement_type": "MOVEMENT_TYPE_FACE_RIGHT",
      "movement_range_x": 0,
      "movement_range_y": 0,
      "trainer_type": "TRAINER_TYPE_NONE",
      "trainer_sight_or_berry_tree_id": "0",
      "script": "BKFORT_4F_NPC_3",
      "flag": "0"
    },
    {
      "graphics_id": "OBJ_EVENT_GFX_ELITE_BLACK_KNIGHT",
      "x": 16,
      "y": 24,
      "elevation": 0,
      "movement_type": "MOVEMENT_TYPE_NONE",
      "movement_range_x": 0,
      "movement_range_y": 0,
      "trainer_type": "TRAINER_TYPE_NONE",
      "trainer_sight_or_berry_tree_id": "0",
      "script": "BKFORT_4F_NPC_2",
      "flag": "0"
    },
    {
      "graphics_id": "OBJ_EVENT_GFX_ITEM_POUCH",
      "x": 7,
      "y": 5,
      "elevation": 0,
      "movement_type": "MOVEMENT_TYPE_NONE",
      "movement_range_x": 0,
      "movement_range_y": 0,
      "trainer_type": "TRAINER_TYPE_NONE",
      "trainer_sight_or_berry_tree_id": "0",
      "script": "ITEM_BKFORT_4F_ITEM4",
      "flag": "FLAG_ITEM_BKFORT_4F_ITEM4"
    },
    {
      "graphics_id": "OBJ_EVENT_GFX_ITEM_POUCH",
      "x": 5,
      "y": 5,
      "elevation": 0,
      "movement_type": "MOVEMENT_TYPE_NONE",
      "movement_range_x": 0,
      "movement_range_y": 0,
      "trainer_type": "TRAINER_TYPE_NONE",
      "trainer_sight_or_berry_tree_id": "0",
      "script": "ITEM_BKFORT_4F_ITEM3",
      "flag": "FLAG_ITEM_BKFORT_4F_ITEM3"
    },
    {
      "graphics_id": "OBJ_EVENT_GFX_ITEM_POUCH",
      "x": 3,
      "y": 5,
      "elevation": 0,
      "movement_type": "MOVEMENT_TYPE_NONE",
      "movement_range_x": 0,
      "movement_range_y": 0,
      "trainer_type": "TRAINER_TYPE_NONE",
      "trainer_sight_or_berry_tree_id": "0",
      "script": "ITEM_BKFORT_4F_ITEM2",
      "flag": "FLAG_ITEM_BKFORT_4F_ITEM2"
    },
    {
      "graphics_id": "OBJ_EVENT_GFX_ITEM_POUCH",
      "x": 6,
      "y": 6,
      "elevation": 0,
      "movement_type": "MOVEMENT_TYPE_NONE",
      "movement_range_x": 0,
      "movement_range_y": 0,
      "trainer_type": "TRAINER_TYPE_NONE",
      "trainer_sight_or_berry_tree_id": "0",
      "script": "ITEM_BKFORT_4F_ITEM5",
      "flag": "FLAG_ITEM_BKFORT_4F_ITEM5"
    },
    {
      "graphics_id": "OBJ_EVENT_GFX_ITEM_POUCH",
      "x": 1,
      "y": 7,
      "elevation": 0,
      "movement_type": "MOVEMENT_TYPE_NONE",
      "movement_range_x": 0,
      "movement_range_y": 0,
      "trainer_type": "TRAINER_TYPE_NONE",
      "trainer_sight_or_berry_tree_id": "0",
      "script": "ITEM_BKFORT_4F_ITEM1",
      "flag": "FLAG_ITEM_BKFORT_4F_ITEM1"
    },
    {
      "graphics_id": "OBJ_EVENT_GFX_KNIGHT_BLACK_M",
      "x": 10,
      "y": 27,
      "elevation": 0,
      "movement_type": "MOVEMENT_TYPE_FACE_RIGHT",
      "movement_range_x": 0,
      "movement_range_y": 0,
      "trainer_type": "TRAINER_TYPE_NONE",
      "trainer_sight_or_berry_tree_id": "0",
      "script": "BKFORT_4F_NPC_1",
      "flag": "0"
    },
    {
      "graphics_id": "OBJ_EVENT_GFX_ITEM_POUCH",
      "x": 6,
      "y": 8,
      "elevation": 0,
      "movement_type": "MOVEMENT_TYPE_NONE",
      "movement_range_x": 0,
      "movement_range_y": 0,
      "trainer_type": "TRAINER_TYPE_NONE",
      "trainer_sight_or_berry_tree_id": "0",
      "script": "ITEM_BKFORT_4F_ITEM6",
      "flag": "FLAG_ITEM_BKFORT_4F_ITEM6"
    },
    {
      "graphics_id": "OBJ_EVENT_GFX_KNIGHT_BLACK_M",
      "x": 16,
      "y": 4,
      "elevation": 0,
      "movement_type": "MOVEMENT_TYPE_FACE_RIGHT",
      "movement_range_x": 0,
      "movement_range_y": 0,
      "trainer_type": "TRAINER_TYPE_NONE",
      "trainer_sight_or_berry_tree_id": "0",
      "script": "BKFORT_4F_NPC_7",
      "flag": "0"
    },
    {
      "graphics_id": "OBJ_EVENT_GFX_IRON_ORE",
      "x": 18,
      "y": 3,
      "elevation": 0,
      "movement_type": "MOVEMENT_TYPE_NONE",
      "movement_range_x": 0,
      "movement_range_y": 0,
      "trainer_type": "TRAINER_TYPE_NONE",
      "trainer_sight_or_berry_tree_id": "0",
      "script": "NULL",
      "flag": "0"
    },
    {
      "graphics_id": "OBJ_EVENT_GFX_KNIGHT_BLACK_F",
      "x": 20,
      "y": 21,
      "elevation": 0,
      "movement_type": "MOVEMENT_TYPE_FACE_RIGHT",
      "movement_range_x": 0,
      "movement_range_y": 0,
      "trainer_type": "TRAINER_TYPE_NONE",
      "trainer_sight_or_berry_tree_id": "0",
      "script": "BKFORT_4F_NPC_4",
      "flag": "0"
    },
    {
      "graphics_id": "OBJ_EVENT_GFX_KNIGHT_BLACK_M",
      "x": 10,
      "y": 21,
      "elevation": 0,
      "movement_type": "MOVEMENT_TYPE_FACE_UP",
      "movement_range_x": 0,
      "movement_range_y": 0,
      "trainer_type": "TRAINER_TYPE_NONE",
      "trainer_sight_or_berry_tree_id": "0",
      "script": "BKFORT_4F_NPC_3",
      "flag": "0"
    }
  ],
  "warp_events": [
    {
      "x": 16,
      "y": 29,
      "elevation": 0,
      "dest_map": "MAP_BLACK_KNIGHTS_FORTRESS_2",
      "dest_warp_id": "1"
    }
  ],
  "coord_events": [
    {
      "type": "trigger",
      "x": 15,
      "y": 26,
      "elevation": 0,
      "var": "VAR_TEMP_0",
      "var_value": "0",
      "script": "TRIGGER_BLACK_KNIGHT_4F_1"
    },
    {
      "type": "trigger",
      "x": 17,
      "y": 26,
      "elevation": 0,
      "var": "VAR_TEMP_0",
      "var_value": "0",
      "script": "TRIGGER_BLACK_KNIGHT_4F_1"
    },
    {
      "type": "trigger",
      "x": 16,
      "y": 26,
      "elevation": 0,
      "var": "VAR_TEMP_0",
      "var_value": "0",
      "script": "TRIGGER_BLACK_KNIGHT_4F_1"
    },
    {
      "type": "trigger",
      "x": 16,
      "y": 11,
      "elevation": 0,
      "var": "VAR_POKESCAPE_STORYMODE_PROGRESS",
      "var_value": "192",
      "script": "TRIGGER_BLACK_KNIGHT_4F_FINAL"
    },
    {
      "type": "trigger",
      "x": 16,
      "y": 7,
      "elevation": 0,
      "var": "VAR_TEMP_0",
      "var_value": "0",
      "script": "NULL"
    },
    {
      "type": "trigger",
      "x": 15,
      "y": 22,
      "elevation": 0,
      "var": "VAR_TEMP_0",
      "var_value": "0",
      "script": "NULL"
    },
    {
      "type": "trigger",
      "x": 16,
      "y": 22,
      "elevation": 0,
      "var": "VAR_TEMP_0",
      "var_value": "0",
      "script": "NULL"
    },
    {
      "type": "trigger",
      "x": 17,
      "y": 22,
      "elevation": 0,
      "var": "VAR_TEMP_0",
      "var_value": "0",
      "script": "NULL"
    },
    {
      "type": "trigger",
      "x": 2,
      "y": 13,
      "elevation": 0,
      "var": "VAR_TEMP_0",
      "var_value": "0",
      "script": "TRIGGER_BLACK_KNIGHT_4F_TREASURE"
    },
    {
      "type": "trigger",
      "x": 3,
      "y": 13,
      "elevation": 0,
      "var": "VAR_TEMP_0",
      "var_value": "0",
      "script": "TRIGGER_BLACK_KNIGHT_4F_TREASURE"
    },
    {
      "type": "trigger",
      "x": 1,
      "y": 13,
      "elevation": 0,
      "var": "VAR_TEMP_0",
      "var_value": "0",
      "script": "TRIGGER_BLACK_KNIGHT_4F_TREASURE"
    }
  ],
  "bg_events": [
    {
      "type": "sign",
      "x": 11,
      "y": 27,
      "elevation": 0,
      "player_facing_dir": "BG_EVENT_PLAYER_FACING_ANY",
      "script": "BKFORT_4F_PLANT"
    },
    {
      "type": "sign",
      "x": 11,
      "y": 21,
      "elevation": 0,
      "player_facing_dir": "BG_EVENT_PLAYER_FACING_ANY",
      "script": "BKFORT_4F_BOOK_1"
    },
    {
      "type": "sign",
      "x": 12,
      "y": 21,
      "elevation": 0,
      "player_facing_dir": "BG_EVENT_PLAYER_FACING_ANY",
      "script": "BKFORT_4F_BOOK_1"
    },
    {
      "type": "sign",
      "x": 20,
      "y": 13,
      "elevation": 0,
      "player_facing_dir": "BG_EVENT_PLAYER_FACING_ANY",
      "script": "BKFORT_4F_BOOK_2"
    },
    {
      "type": "sign",
      "x": 21,
      "y": 13,
      "elevation": 0,
      "player_facing_dir": "BG_EVENT_PLAYER_FACING_ANY",
      "script": "BKFORT_4F_BOOK_3"
    }
  ],
  "has_night_table": false
}
