{
  "id": "MAP_ICE_MOUNTAIN",
  "name": "Ice_Mountain",
  "layout": "LAYOUT_ICE_MOUNTAIN",
  "music": "MUS_CAVE_OF_ORIGIN",
  "region_map_section": "MAPSEC_DWARVEN_MINES",
  "requires_flash": false,
  "weather": "WEATHER_NONE",
  "map_type": "MAP_TYPE_ROUTE",
  "allow_cycling": true,
  "allow_escaping": false,
  "allow_running": true,
  "show_map_name": true,
  "battle_scene": "MAP_BATTLE_SCENE_NORMAL",
  "connections": [
    {
      "map": "MAP_ROUTE26",
      "offset": 0,
      "direction": "down"
    },
    {
      "map": "MAP_ROUTE27",
      "offset": 26,
      "direction": "down"
    }
  ],
  "object_events": [

  ],
  "warp_events": [

  ],
  "coord_events": [

  ],
  "bg_events": [

  ],
  "has_night_table": false
}
