{
  "id": "MAP_PURO_PURO3",
  "name": "Puro_Puro3",
  "layout": "LAYOUT_PURO_PURO3",
  "music": "MUS_DUMMY",
  "region_map_section": "MAPSEC_ROUTE_1",
  "requires_flash": false,
  "weather": "WEATHER_NONE",
  "map_type": "MAP_TYPE_NONE",
  "allow_cycling": false,
  "allow_escaping": false,
  "allow_running": true,
  "show_map_name": true,
  "battle_scene": "MAP_BATTLE_SCENE_NORMAL",
  "connections": 0,
  "object_events": [
    {
      "graphics_id": "OBJ_EVENT_GFX_IMP",
      "x": 13,
      "y": 15,
      "elevation": 0,
      "movement_type": "MOVEMENT_TYPE_WANDER_AROUND",
      "movement_range_x": 2,
      "movement_range_y": 2,
      "trainer_type": "TRAINER_TYPE_NONE",
      "trainer_sight_or_berry_tree_id": "0",
      "script": "IMMENIZZ",
      "flag": "0"
    },
    {
      "graphics_id": "OBJ_EVENT_GFX_IMP",
      "x": 23,
      "y": 24,
      "elevation": 0,
      "movement_type": "MOVEMENT_TYPE_WANDER_LEFT_AND_RIGHT",
      "movement_range_x": 4,
      "movement_range_y": 1,
      "trainer_type": "TRAINER_TYPE_NONE",
      "trainer_sight_or_berry_tree_id": "0",
      "script": "ENCOUNTER_PURO_PURO_3",
      "flag": "FLAG_TEMP_3"
    },
    {
      "graphics_id": "OBJ_EVENT_GFX_FAIRY_3",
      "x": 7,
      "y": 23,
      "elevation": 0,
      "movement_type": "MOVEMENT_TYPE_WANDER_RIGHT_AND_LEFT",
      "movement_range_x": 6,
      "movement_range_y": 1,
      "trainer_type": "TRAINER_TYPE_NONE",
      "trainer_sight_or_berry_tree_id": "0",
      "script": "PURO_FAIRY_3",
      "flag": "0"
    },
    {
      "graphics_id": "OBJ_EVENT_GFX_HUNTER_F",
      "x": 4,
      "y": 6,
      "elevation": 0,
      "movement_type": "MOVEMENT_TYPE_NONE",
      "movement_range_x": 0,
      "movement_range_y": 0,
      "trainer_type": "TRAINER_TYPE_NONE",
      "trainer_sight_or_berry_tree_id": "0",
      "script": "PURO_HUNTER_3",
      "flag": "0"
    },
    {
      "graphics_id": "OBJ_EVENT_GFX_IMP",
      "x": 20,
      "y": 15,
      "elevation": 0,
      "movement_type": "MOVEMENT_TYPE_WANDER_UP_AND_DOWN",
      "movement_range_x": 1,
      "movement_range_y": 6,
      "trainer_type": "TRAINER_TYPE_NONE",
      "trainer_sight_or_berry_tree_id": "0",
      "script": "IMP_DEFENDER",
      "flag": "0"
    },
    {
      "graphics_id": "OBJ_EVENT_GFX_GNOME_CHILD",
      "x": 17,
      "y": 13,
      "elevation": 0,
      "movement_type": "MOVEMENT_TYPE_LOOK_AROUND",
      "movement_range_x": 0,
      "movement_range_y": 0,
      "trainer_type": "TRAINER_TYPE_NONE",
      "trainer_sight_or_berry_tree_id": "0",
      "script": "ELNOCK_3",
      "flag": "0"
    },
    {
      "graphics_id": "OBJ_EVENT_GFX_IMP",
      "x": 11,
      "y": 9,
      "elevation": 0,
      "movement_type": "MOVEMENT_TYPE_WANDER_LEFT_AND_RIGHT",
      "movement_range_x": 4,
      "movement_range_y": 1,
      "trainer_type": "TRAINER_TYPE_NONE",
      "trainer_sight_or_berry_tree_id": "0",
      "script": "IMP_DEFENDER",
      "flag": "0"
    },
    {
      "graphics_id": "OBJ_EVENT_GFX_IMP",
      "x": 20,
      "y": 5,
      "elevation": 0,
      "movement_type": "MOVEMENT_TYPE_WANDER_AROUND",
      "movement_range_x": 1,
      "movement_range_y": 2,
      "trainer_type": "TRAINER_TYPE_NONE",
      "trainer_sight_or_berry_tree_id": "0",
      "script": "ENCOUNTER_PURO_PURO_3",
      "flag": "FLAG_TEMP_1"
    },
    {
      "graphics_id": "OBJ_EVENT_GFX_IMP",
      "x": 8,
      "y": 17,
      "elevation": 0,
      "movement_type": "MOVEMENT_TYPE_WANDER_UP_AND_DOWN",
      "movement_range_x": 1,
      "movement_range_y": 4,
      "trainer_type": "TRAINER_TYPE_NONE",
      "trainer_sight_or_berry_tree_id": "0",
      "script": "ENCOUNTER_PURO_PURO_3",
      "flag": "FLAG_TEMP_2"
    },
    {
      "graphics_id": "OBJ_EVENT_GFX_ITEM_POUCH",
      "x": 25,
      "y": 5,
      "elevation": 0,
      "movement_type": "MOVEMENT_TYPE_NONE",
      "movement_range_x": 0,
      "movement_range_y": 0,
      "trainer_type": "TRAINER_TYPE_NONE",
      "trainer_sight_or_berry_tree_id": "0",
      "script": "ITEM_PURO_PURO_3",
      "flag": "FLAG_ITEM_PURO_PURO_3"
    },
    {
      "graphics_id": "OBJ_EVENT_GFX_IRONMAN",
      "x": 25,
      "y": 14,
      "elevation": 0,
      "movement_type": "MOVEMENT_TYPE_FACE_DOWN_AND_LEFT",
      "movement_range_x": 0,
      "movement_range_y": 0,
      "trainer_type": "TRAINER_TYPE_NONE",
      "trainer_sight_or_berry_tree_id": "0",
      "script": "PURO_IRONMAN_3",
      "flag": "0"
    }
  ],
  "warp_events": [
    {
      "x": 14,
      "y": 13,
      "elevation": 0,
      "dest_map": "MAP_ROUTE13",
      "dest_warp_id": "1"
    }
  ],
  "coord_events": [

  ],
  "bg_events": [

  ]
}
